hypercourse/__cli__.py
hypercourse/__init__.py
hypercourse/_version.py
hypercourse/py.typed
hypercourse/conf/about/hypercourse.yaml
hyperfast_course_template-0.2.1.dist-info/METADATA
hyperfast_course_template-0.2.1.dist-info/WHEEL
hyperfast_course_template-0.2.1.dist-info/entry_points.txt
hyperfast_course_template-0.2.1.dist-info/licenses/LICENSE
hyperfast_course_template-0.2.1.dist-info/RECORD
