Metadata-Version: 2.4
Name: hyperfast-course-template
Version: 0.2.1
Summary: Multilingual course creation template with interactive documentation support for international audiences
Project-URL: Homepage, https://hypercourse.entelecheia.ai
Project-URL: Repository, https://github.com/entelecheia/hyperfast-course-template
Project-URL: Documentation, https://hypercourse.entelecheia.ai
Author-email: Young Joon Lee <entelecheia@hotmail.com>
License-Expression: CC-BY-4.0
License-File: LICENSE
Keywords: python
Classifier: Intended Audience :: Developers
Classifier: Programming Language :: Python
Classifier: Programming Language :: Python :: 3
Classifier: Programming Language :: Python :: 3.9
Classifier: Programming Language :: Python :: 3.10
Classifier: Programming Language :: Python :: 3.11
Classifier: Programming Language :: Python :: 3.12
Classifier: Programming Language :: Python :: 3.13
Classifier: Topic :: Software Development :: Libraries :: Python Modules
Requires-Python: <4.0,>=3.9
Requires-Dist: click>=8.1.7
